UniParse/__init__.py
UniParse/parser.py
UniParse/resume_parser.py
UniParse/resume_summary.py
UniParse-1.0.1.dist-info/LICENSE
UniParse-1.0.1.dist-info/METADATA
UniParse-1.0.1.dist-info/WHEEL
UniParse-1.0.1.dist-info/top_level.txt
UniParse-1.0.1.dist-info/RECORD
